[{"word": "technology", "word_count": 7, "doc_ID": ["41-def4"]}, {"word": "britannica.com", "word_count": 5, "doc_ID": ["44-def4", "43-def4", "42-def4", "41-def4", "40-def4"]}, {"word": "either", "word_count": 3, "doc_ID": ["41-def4", "40-def4"]}, {"word": "wi-fi", "word_count": 8, "doc_ID": ["44-def4"]}, {"word": "giza", "word_count": 3, "doc_ID": ["40-def4"]}, {"word": "power", "word_count": 4, "doc_ID": ["41-def4", "40-def4"]}, {"word": "time", "word_count": 5, "doc_ID": ["41-def4", "44-def4", "40-def4"]}, {"word": "never", "word_count": 3, "doc_ID": ["40-def4", "43-def4"]}, {"word": "schizophrenia", "word_count": 6, "doc_ID": ["43-def4"]}, {"word": "galaxy", "word_count": 6, "doc_ID": ["41-def4"]}, {"word": "years", "word_count": 5, "doc_ID": ["41-def4"]}, {"word": "also", "word_count": 3, "doc_ID": ["42-def4", "41-def4"]}, {"word": "found", "word_count": 5, "doc_ID": ["43-def4", "42-def4", "40-def4"]}, {"word": "waves", "word_count": 4, "doc_ID": ["44-def4"]}, {"word": "like", "word_count": 4, "doc_ID": ["40-def4", "44-def4", "41-def4"]}, {"word": "cause", "word_count": 3, "doc_ID": ["43-def4"]}, {"word": "scale", "word_count": 4, "doc_ID": ["41-def4"]}, {"word": "though", "word_count": 3, "doc_ID": ["44-def4", "43-def4", "42-def4"]}, {"word": "per", "word_count": 4, "doc_ID": ["44-def4"]}, {"word": "said", "word_count": 3, "doc_ID": ["41-def4", "40-def4"]}, {"word": "10", "word_count": 5, "doc_ID": ["41-def4"]}, {"word": "long", "word_count": 3, "doc_ID": ["42-def4", "41-def4", "40-def4"]}, {"word": "according", "word_count": 3, "doc_ID": ["41-def4", "40-def4"]}, {"word": "one", "word_count": 8, "doc_ID": ["44-def4", "41-def4", "43-def4", "42-def4"]}, {"word": "channels", "word_count": 3, "doc_ID": ["44-def4"]}, {"word": "number", "word_count": 4, "doc_ID": ["41-def4", "42-def4", "40-def4"]}, {"word": "gigahertz", "word_count": 3, "doc_ID": ["44-def4"]}, {"word": "could", "word_count": 10, "doc_ID": ["41-def4", "40-def4", "43-def4"]}, {"word": "universe", "word_count": 4, "doc_ID": ["41-def4"]}, {"word": "across", "word_count": 6, "doc_ID": ["41-def4", "44-def4"]}, {"word": "many", "word_count": 6, "doc_ID": ["42-def4", "41-def4", "43-def4"]}, {"word": "sustain", "word_count": 3, "doc_ID": ["41-def4", "42-def4"]}, {"word": "radio", "word_count": 3, "doc_ID": ["44-def4", "41-def4"]}, {"word": "incorrupt", "word_count": 4, "doc_ID": ["42-def4"]}, {"word": "chambers", "word_count": 3, "doc_ID": ["40-def4"]}, {"word": "originally", "word_count": 3, "doc_ID": ["40-def4", "41-def4"]}, {"word": "stars", "word_count": 4, "doc_ID": ["41-def4"]}, {"word": "would", "word_count": 9, "doc_ID": ["40-def4", "42-def4", "41-def4"]}, {"word": "type", "word_count": 5, "doc_ID": ["41-def4"]}, {"word": "explanations", "word_count": 3, "doc_ID": ["41-def4", "42-def4"]}, {"word": "gondii", "word_count": 3, "doc_ID": ["43-def4"]}, {"word": "life", "word_count": 13, "doc_ID": ["41-def4", "40-def4"]}, {"word": "filter", "word_count": 3, "doc_ID": ["41-def4"]}, {"word": "drake", "word_count": 5, "doc_ID": ["41-def4"]}, {"word": "signals", "word_count": 3, "doc_ID": ["41-def4"]}, {"word": "well", "word_count": 6, "doc_ID": ["44-def4", "40-def4", "43-def4", "41-def4"]}, {"word": "frequency", "word_count": 4, "doc_ID": ["44-def4"]}, {"word": "0s", "word_count": 4, "doc_ID": ["44-def4"]}, {"word": "existence", "word_count": 3, "doc_ID": ["41-def4"]}, {"word": "chamber", "word_count": 7, "doc_ID": ["40-def4"]}, {"word": "live", "word_count": 3, "doc_ID": ["41-def4"]}, {"word": "scientists", "word_count": 9, "doc_ID": ["41-def4"]}, {"word": "question", "word_count": 5, "doc_ID": ["41-def4"]}, {"word": "usually", "word_count": 3, "doc_ID": ["43-def4", "42-def4", "40-def4"]}, {"word": "may", "word_count": 3, "doc_ID": ["41-def4", "42-def4"]}, {"word": "inside", "word_count": 6, "doc_ID": ["40-def4"]}, {"word": "internet", "word_count": 5, "doc_ID": ["44-def4"]}, {"word": "way", "word_count": 3, "doc_ID": ["41-def4"]}, {"word": "=", "word_count": 4, "doc_ID": ["41-def4"]}, {"word": "paradox", "word_count": 3, "doc_ID": ["41-def4"]}, {"word": "burial", "word_count": 4, "doc_ID": ["40-def4", "42-def4"]}, {"word": "deterioration", "word_count": 4, "doc_ID": ["43-def4"]}, {"word": "imagine", "word_count": 3, "doc_ID": ["40-def4"]}, {"word": "wax", "word_count": 4, "doc_ID": ["42-def4"]}, {"word": "still", "word_count": 3, "doc_ID": ["41-def4", "43-def4"]}, {"word": "bodies", "word_count": 5, "doc_ID": ["42-def4"]}, {"word": "king", "word_count": 5, "doc_ID": ["40-def4"]}, {"word": "n", "word_count": 5, "doc_ID": ["41-def4"]}, {"word": "silence", "word_count": 3, "doc_ID": ["41-def4"]}, {"word": "incorruptibility", "word_count": 3, "doc_ID": ["42-def4"]}, {"word": "communication", "word_count": 4, "doc_ID": ["41-def4"]}, {"word": "space", "word_count": 4, "doc_ID": ["41-def4", "40-def4"]}, {"word": "us", "word_count": 9, "doc_ID": ["41-def4", "42-def4"]}, {"word": "answer", "word_count": 3, "doc_ID": ["41-def4", "40-def4"]}, {"word": "probably", "word_count": 3, "doc_ID": ["44-def4", "43-def4", "41-def4"]}, {"word": "kardashev", "word_count": 4, "doc_ID": ["41-def4"]}, {"word": "pyramid", "word_count": 13, "doc_ID": ["40-def4"]}, {"word": "seen", "word_count": 3, "doc_ID": ["40-def4"]}, {"word": "1s", "word_count": 4, "doc_ID": ["44-def4"]}, {"word": "cats", "word_count": 6, "doc_ID": ["43-def4"]}, {"word": "possibly", "word_count": 3, "doc_ID": ["43-def4", "41-def4", "40-def4"]}, {"word": "transmission", "word_count": 3, "doc_ID": ["41-def4"]}, {"word": "second", "word_count": 5, "doc_ID": ["44-def4"]}, {"word": "developing", "word_count": 4, "doc_ID": ["41-def4"]}, {"word": "travel", "word_count": 3, "doc_ID": ["41-def4", "44-def4"]}, {"word": "wall", "word_count": 3, "doc_ID": ["41-def4"]}, {"word": "saints", "word_count": 3, "doc_ID": ["42-def4"]}, {"word": "frequencies", "word_count": 6, "doc_ID": ["44-def4"]}, {"word": "two", "word_count": 3, "doc_ID": ["44-def4", "41-def4"]}, {"word": "limestone", "word_count": 3, "doc_ID": ["40-def4"]}, {"word": "equation", "word_count": 8, "doc_ID": ["41-def4"]}, {"word": "alone", "word_count": 3, "doc_ID": ["42-def4", "41-def4", "40-def4"]}, {"word": "router", "word_count": 4, "doc_ID": ["44-def4"]}, {"word": "napoleon", "word_count": 5, "doc_ID": ["40-def4"]}, {"word": "device", "word_count": 4, "doc_ID": ["44-def4"]}, {"word": "century", "word_count": 3, "doc_ID": ["41-def4", "40-def4"]}, {"word": "fraction", "word_count": 4, "doc_ID": ["41-def4"]}, {"word": "rot", "word_count": 3, "doc_ID": ["42-def4"]}, {"word": "body", "word_count": 6, "doc_ID": ["42-def4"]}, {"word": "pyramids", "word_count": 10, "doc_ID": ["40-def4"]}, {"word": "develop", "word_count": 4, "doc_ID": ["41-def4", "43-def4"]}, {"word": "civilization", "word_count": 3, "doc_ID": ["41-def4"]}, {"word": "fermi", "word_count": 5, "doc_ID": ["41-def4"]}, {"word": "often", "word_count": 3, "doc_ID": ["42-def4", "40-def4"]}, {"word": "great", "word_count": 16, "doc_ID": ["40-def4", "41-def4", "42-def4"]}, {"word": "data", "word_count": 5, "doc_ID": ["44-def4"]}, {"word": "even", "word_count": 6, "doc_ID": ["41-def4", "40-def4"]}, {"word": "wave", "word_count": 3, "doc_ID": ["44-def4"]}, {"word": "binary", "word_count": 4, "doc_ID": ["44-def4"]}, {"word": "code", "word_count": 4, "doc_ID": ["44-def4"]}, {"word": "although", "word_count": 3, "doc_ID": ["43-def4", "42-def4", "40-def4"]}, {"word": "intelligent", "word_count": 10, "doc_ID": ["41-def4"]}, {"word": "three", "word_count": 3, "doc_ID": ["40-def4", "41-def4"]}, {"word": "civilizations", "word_count": 14, "doc_ID": ["41-def4"]}, {"word": "\u00d7", "word_count": 6, "doc_ID": ["41-def4"]}, {"word": "holy", "word_count": 3, "doc_ID": ["42-def4"]}, {"word": "planets", "word_count": 4, "doc_ID": ["41-def4"]}]